odoo10_addon_procurement_analytic-10.0.1.2.0-py2.7-nspkg.pth
odoo/addons/procurement_analytic/README.rst
odoo/addons/procurement_analytic/__init__.py
odoo/addons/procurement_analytic/__manifest__.py
odoo/addons/procurement_analytic/i18n/ca.po
odoo/addons/procurement_analytic/i18n/cs_CZ.po
odoo/addons/procurement_analytic/i18n/de.po
odoo/addons/procurement_analytic/i18n/el_GR.po
odoo/addons/procurement_analytic/i18n/es.po
odoo/addons/procurement_analytic/i18n/es_EC.po
odoo/addons/procurement_analytic/i18n/es_MX.po
odoo/addons/procurement_analytic/i18n/fi.po
odoo/addons/procurement_analytic/i18n/fr.po
odoo/addons/procurement_analytic/i18n/gu_IN.po
odoo/addons/procurement_analytic/i18n/hi_IN.po
odoo/addons/procurement_analytic/i18n/hr.po
odoo/addons/procurement_analytic/i18n/hr_HR.po
odoo/addons/procurement_analytic/i18n/it.po
odoo/addons/procurement_analytic/i18n/nl.po
odoo/addons/procurement_analytic/i18n/procurement_analytic.pot
odoo/addons/procurement_analytic/i18n/pt_BR.po
odoo/addons/procurement_analytic/i18n/pt_PT.po
odoo/addons/procurement_analytic/i18n/sk_SK.po
odoo/addons/procurement_analytic/i18n/sl.po
odoo/addons/procurement_analytic/i18n/tr_TR.po
odoo/addons/procurement_analytic/i18n/zh_CN.po
odoo/addons/procurement_analytic/models/__init__.py
odoo/addons/procurement_analytic/models/account_analytic_account.py
odoo/addons/procurement_analytic/models/procurement.py
odoo/addons/procurement_analytic/static/description/icon.png
odoo/addons/procurement_analytic/views/account_analytic_account_view.xml
odoo/addons/procurement_analytic/views/procurement_analytic.xml
odoo10_addon_procurement_analytic-10.0.1.2.0.dist-info/DESCRIPTION.rst
odoo10_addon_procurement_analytic-10.0.1.2.0.dist-info/METADATA
odoo10_addon_procurement_analytic-10.0.1.2.0.dist-info/RECORD
odoo10_addon_procurement_analytic-10.0.1.2.0.dist-info/WHEEL
odoo10_addon_procurement_analytic-10.0.1.2.0.dist-info/metadata.json
odoo10_addon_procurement_analytic-10.0.1.2.0.dist-info/namespace_packages.txt
odoo10_addon_procurement_analytic-10.0.1.2.0.dist-info/top_level.txt
